<?xml version="1.0" encoding="UTF-8"?>
<!DOCTYPE suite SYSTEM "http://testng.org/testng-1.0.dtd">
<suite name="All Test Suite" parallel="tests" thread-count="2">

    <test name="Test 1">
        <parameter name="browserName" value="firefox"/>
        <classes>
            <class name="page_tests.GoogleSearchTests"/>
        </classes>
    </test>


<!--    <test name="3 Google Search Test">-->
<!--        <parameter name="browserName" value="firefox"/>-->
<!--        <classes>-->
<!--            <class name="page_tests.GoogleSearchImFeelingLuckyTests">-->
<!--                <methods>-->
<!--                    <include name="click2ndLink"/>-->
<!--                </methods>-->
<!--            </class>-->
<!--        </classes>-->
<!--    </test>-->

<!--    <test name="4 Google Search I m Feeling Test">-->
<!--        <parameter name="browserName" value="chrome"/>-->
<!--        <classes>-->
<!--            <class name="page_tests.GoogleSearchTests">-->
<!--                <methods>-->
<!--                    <include name="testGoogleSearch"/>-->
<!--                </methods>-->
<!--            </class>-->
<!--        </classes>-->
<!--    </test>-->


</suite>